satisfactory_api_client/__init__.py
satisfactory_api_client/api_client.py
satisfactory_api_client/config.py
satisfactory_api_client/exceptions.py
satisfactory_api_client/utils.py
satisfactory_api_client/data/__init__.py
satisfactory_api_client/data/advanced_game_settings.py
satisfactory_api_client/data/minimum_privilege_level.py
satisfactory_api_client/data/new_game_save.py
satisfactory_api_client/data/response.py
satisfactory_api_client/data/server_options.py
satisfactory_api_client-0.1.12.dist-info/LICENSE
satisfactory_api_client-0.1.12.dist-info/METADATA
satisfactory_api_client-0.1.12.dist-info/WHEEL
satisfactory_api_client-0.1.12.dist-info/top_level.txt
satisfactory_api_client-0.1.12.dist-info/RECORD
