Metadata-Version: 2.1
Name: satisfactory_api_client
Version: 0.1.12
Summary: A Python Package for interacting with the Satisfactory Dedicated Server API
Home-page: https://github.com/Programmer-Timmy/satisfactory-dedicated-server-api-SDK
Author: Programmer-Timmy
License: MIT
Classifier: Programming Language :: Python :: 3
Classifier: License :: OSI Approved :: MIT License
Classifier: Operating System :: OS Independent
Requires-Python: >=3.6
License-File: LICENSE
Requires-Dist: python-dotenv~=1.0.1
Requires-Dist: requests~=2.32.3
